Metadata-Version: 2.1
Name: odoo-addon-purchase_open_qty
Version: 18.0.1.0.1
Requires-Python: >=3.10
Requires-Dist: odoo-addon-purchase_order_line_menu==18.0.*
Requires-Dist: odoo==18.0.*
Summary: Allows to identify the purchase orders that have quantities pending to invoice or to receive.
Home-page: https://github.com/OCA/purchase-workflow
License: AGPL-3
Author: ForgeFlow, Odoo Community Association (OCA)
Author-email: support@odoo-community.org
Classifier: Programming Language :: Python
Classifier: Framework :: Odoo
Classifier: Framework :: Odoo :: 18.0
Classifier: License :: OSI Approved :: GNU Affero General Public License v3
